home/fabien/devel/public/nautilus-terminal/nautils-terminal-v3/__env__/share/glib-2.0/schemas/gschemas.compiled
home/fabien/devel/public/nautilus-terminal/nautils-terminal-v3/__env__/share/glib-2.0/schemas/org.flozz.nautilus-terminal.gschema.xml
home/fabien/devel/public/nautilus-terminal/nautils-terminal-v3/__env__/share/nautilus-python/extensions/nautilus_terminal_extension.py
nautilus_terminal/__init__.py
nautilus_terminal/__main__.py
nautilus_terminal/about_dialog.py
nautilus_terminal/color_helpers.py
nautilus_terminal/crowbar.py
nautilus_terminal/debug.py
nautilus_terminal/helpers.py
nautilus_terminal/install_nautilus_extension.py
nautilus_terminal/logger.py
nautilus_terminal/nautilus_accels_helpers.py
nautilus_terminal/nautilus_terminal.py
nautilus_terminal/nautilus_terminal_extension.py
nautilus_terminal/not_packaged.py
nautilus_terminal/images/nautilus-terminal-logo.svg
nautilus_terminal/schemas/gschemas.compiled
nautilus_terminal/schemas/org.flozz.nautilus-terminal.gschema.xml
nautilus_terminal-4.1.0.dist-info/COPYING
nautilus_terminal-4.1.0.dist-info/METADATA
nautilus_terminal-4.1.0.dist-info/WHEEL
nautilus_terminal-4.1.0.dist-info/entry_points.txt
nautilus_terminal-4.1.0.dist-info/top_level.txt
nautilus_terminal-4.1.0.dist-info/RECORD
