Metadata-Version: 2.1
Name: nautilus-terminal
Version: 4.1.0
Summary: A terminal embedded in Nautilus, the GNOME's file browser
Home-page: https://github.com/flozz/nautilus-terminal
Author: Fabien LOISON
License: GPL-3.0
Keywords: nautilus extension terminal gnome
Platform: Linux
Platform: BSD
License-File: COPYING
Requires-Dist: psutil (>=5.6.6)
Provides-Extra: dev
Requires-Dist: black ; extra == 'dev'
Requires-Dist: flake8 ; extra == 'dev'
Requires-Dist: nox ; extra == 'dev'
